phylanx/__init__.py
phylanx/_phylanx.cpython-37m-x86_64-linux-gnu.so
phylanx/exceptions.py
phylanx/ast/__init__.py
phylanx/ast/openscop.py
phylanx/ast/physl.py
phylanx/ast/physl_db.py
phylanx/ast/transducer.py
phylanx/ast/utils.py
phylanx/core/__init__.py
phylanx/core/config.py
phylanx/execution_tree/__init__.py
phylanx/plugins/__init__.py
phylanx/plugins/keras.py
phylanx/util/__init__.py
phylanx/util/prange.py
phylanx-libs/libhpx.so.1
phylanx-libs/libhpx_component_storage.so.1
phylanx-libs/libhpx_iostreams.so.1
phylanx-libs/libhpx_partitioned_vector.so.1
phylanx-libs/libhpx_phylanx.so.0
phylanx-libs/libhpx_process.so.1
phylanx-libs/libhpx_unordered.so.1
phylanx-libs/libphylanx_common.so.0
phylanx-libs/boost/libboost_filesystem.so.1.67.0
phylanx-libs/boost/libboost_program_options.so.1.67.0
phylanx-libs/boost/libboost_system.so.1.67.0
phylanx-libs/extras/libatomic.so.1
phylanx-libs/extras/libblas.so.3
phylanx-libs/extras/libgfortran.so.5
phylanx-libs/extras/libhwloc.so.5
phylanx-libs/extras/liblapack.so.3
phylanx-libs/extras/libltdl.so.7
phylanx-libs/extras/libm.so.6
phylanx-libs/extras/libnuma.so.1
phylanx-libs/extras/libquadmath.so.0
phylanx-libs/extras/libtcmalloc_minimal.so.4
phylanx-libs/hpx/libhpx_io_counters.so.1
phylanx-libs/hpx/libhpx_memory.so.1
phylanx-libs/hpx/libhpx_parcel_coalescing.so.1
phylanx-libs/hpx/libhpx_sine.so.1
phylanx-libs/phylanx/libphylanx_algorithms.so
phylanx-libs/phylanx/libphylanx_arithmetics.so
phylanx-libs/phylanx/libphylanx_booleans.so
phylanx-libs/phylanx/libphylanx_controls.so
phylanx-libs/phylanx/libphylanx_dist_keras_support.so
phylanx-libs/phylanx/libphylanx_dist_matrixops.so
phylanx-libs/phylanx/libphylanx_fileio.so
phylanx-libs/phylanx/libphylanx_keras_support.so
phylanx-libs/phylanx/libphylanx_listops.so
phylanx-libs/phylanx/libphylanx_matrixops.so
phylanx-libs/phylanx/libphylanx_solvers.so
phylanx-libs/phylanx/libphylanx_statistics.so
phylanx-0.0.1.dist-info/METADATA
phylanx-0.0.1.dist-info/WHEEL
phylanx-0.0.1.dist-info/top_level.txt
phylanx-0.0.1.dist-info/RECORD
