Metadata-Version: 2.1
Name: phylanx
Version: 0.0.1
Summary: A Python wrapper for the Phylanx execution engine
Home-page: https://github.com/STEllAR-GROUP/phylanx
Author: The STE||AR Group
Author-email: phylanx@stellar-group.org
License: Boost Software License, Version 1.0 (http://www.boost.org/LICENSE_1_0.txt)
Platform: All
